slimfit/__init__.py
slimfit/__version__.py
slimfit/_version.py
slimfit/base.py
slimfit/fit.py
slimfit/fitresult.py
slimfit/functions.py
slimfit/loss.py
slimfit/markov.py
slimfit/minimizers.py
slimfit/models.py
slimfit/np_funcs.py
slimfit/numerical.py
slimfit/objective.py
slimfit/operations.py
slimfit/parameter.py
slimfit/reduce.py
slimfit/symbols.py
slimfit/typing.py
slimfit/utils.py
slimfit-0.1.4.dist-info/METADATA
slimfit-0.1.4.dist-info/WHEEL
slimfit-0.1.4.dist-info/licenses/LICENSE
slimfit-0.1.4.dist-info/RECORD
