Metadata-Version: 2.1
Name: slimfit
Version: 0.1.4
Summary: SymFit's little brother
Project-URL: Source, https://github.com/Jhsmit/slimfit/
Project-URL: Documentation, https://jhsmit.github.io/slimfit/
Author-email: Jochem Smit <jhsmit@gmail.com>
License: MIT License
License-File: LICENSE
Classifier: Development Status :: 2 - Pre-Alpha
Classifier: Intended Audience :: Science/Research
Classifier: Programming Language :: Python :: 3.9
Classifier: Programming Language :: Python :: 3.10
Requires-Python: >=3.9
Requires-Dist: numdifftools
Requires-Dist: numpy
Requires-Dist: pyyaml
Requires-Dist: scipy
Requires-Dist: sympy
Requires-Dist: tqdm
Requires-Dist: typing-extensions
Provides-Extra: dev
Requires-Dist: black[jupyter]>=22.12.0; extra == 'dev'
Requires-Dist: setuptools-scm; extra == 'dev'
Provides-Extra: docs
Requires-Dist: jupyter>=1.0.0; extra == 'docs'
Requires-Dist: mkdocs-gen-files>=0.4.0; extra == 'docs'
Requires-Dist: mkdocs-jupyter>=0.22.0; extra == 'docs'
Requires-Dist: mkdocs-literate-nav>=0.5.0; extra == 'docs'
Requires-Dist: mkdocs-material>=8.5.11; extra == 'docs'
Requires-Dist: mkdocs>=1.4.2; extra == 'docs'
Requires-Dist: mkdocstrings[python]>=0.19.1; extra == 'docs'
Requires-Dist: pygments>=2.13.0; extra == 'docs'
Provides-Extra: plot
Requires-Dist: proplot>=0.9.7; extra == 'plot'
Provides-Extra: test
Requires-Dist: pytest>=7.2.0; extra == 'test'
